README.md
setup.py
pvlv_database/__init__.py
pvlv_database/pvlv_database.py
pvlv_database.egg-info/PKG-INFO
pvlv_database.egg-info/SOURCES.txt
pvlv_database.egg-info/dependency_links.txt
pvlv_database.egg-info/requires.txt
pvlv_database.egg-info/top_level.txt
pvlv_database/cache/__init__.py
pvlv_database/cache/database_cache.py
pvlv_database/cache/item_storage.py
pvlv_database/cache/saving_demon.py
pvlv_database/commands/__init__.py
pvlv_database/commands/commands.py
pvlv_database/common/__init__.py
pvlv_database/common/action_counter_log.py
pvlv_database/common/module_configurations.py
pvlv_database/configurations/__init__.py
pvlv_database/configurations/configuration.py
pvlv_database/connectors/__init__.py
pvlv_database/connectors/connector.py
pvlv_database/guild/__init__.py
pvlv_database/guild/guild.py
pvlv_database/guild/modules/__init__.py
pvlv_database/guild/modules/modules.py
pvlv_database/updaters/__init__.py
pvlv_database/updaters/stats_updater.py
pvlv_database/user/__init__.py
pvlv_database/user/user.py
pvlv_database/user/guild_user/__init__.py
pvlv_database/user/guild_user/guild_user.py
pvlv_database/user/modules/__init__.py
pvlv_database/user/modules/bill.py
pvlv_database/user/modules/commands.py
pvlv_database/user/modules/messages.py
pvlv_database/user/modules/xp.py